pyvikunja/__init__.py
pyvikunja/api.py
pyvikunja/models/label.py
pyvikunja/models/models.py
pyvikunja/models/project.py
pyvikunja/models/task.py
pyvikunja/models/team.py
pyvikunja/models/user.py
pyvikunja/models/enum/repeat_mode.py
pyvikunja/models/enum/task_priority.py
pyvikunja-0.23.dist-info/licenses/LICENSE
pyvikunja-0.23.dist-info/METADATA
pyvikunja-0.23.dist-info/WHEEL
pyvikunja-0.23.dist-info/top_level.txt
pyvikunja-0.23.dist-info/RECORD
