Metadata-Version: 2.4
Name: pyvikunja
Version: 0.23
Summary: A Python wrapper for Vikunja API
Author: Joseph Shufflebotham
License: AGPL
License-File: LICENSE
Requires-Dist: httpx==0.28.1
Dynamic: license-file
